myapp_plugin_hello/__init__.py
myapp_plugin_hello/plugin.py
myapp_plugin_hello-0.1.4.dist-info/licenses/LICENSE
myapp_plugin_hello-0.1.4.dist-info/METADATA
myapp_plugin_hello-0.1.4.dist-info/WHEEL
myapp_plugin_hello-0.1.4.dist-info/entry_points.txt
myapp_plugin_hello-0.1.4.dist-info/top_level.txt
myapp_plugin_hello-0.1.4.dist-info/RECORD
