Metadata-Version: 2.4
Name: myapp-plugin-hello
Version: 0.1.4
Summary: MyApp的Hello插件 - 一个简单的问候插件
Author-email: Sans <your.email@example.com>
Project-URL: Homepage, https://github.com/yourusername/myapp-plugin-hello
Requires-Python: >=3.7
License-File: LICENSE
Requires-Dist: my-app-core
Dynamic: license-file
